django_simpletask2/__init__.py
django_simpletask2/actions.py
django_simpletask2/admin.py
django_simpletask2/apps.py
django_simpletask2/exceptions.py
django_simpletask2/models.py
django_simpletask2/services.py
django_simpletask2/settings.py
django_simpletask2/tests.py
django_simpletask2/urls.py
django_simpletask2/views.py
django_simpletask2/viewshelper.py
django_simpletask2/locale/zh_Hans/LC_MESSAGES/django.mo
django_simpletask2/locale/zh_Hans/LC_MESSAGES/django.po
django_simpletask2/management/__init__.py
django_simpletask2/management/commands/__init__.py
django_simpletask2/management/commands/scan_simpletask_queue.py
django_simpletask2/migrations/0001_initial.py
django_simpletask2/migrations/0002_auto_20231024_1722.py
django_simpletask2/migrations/0003_auto_20231024_1740.py
django_simpletask2/migrations/0004_alter_simpletaskchannel_options.py
django_simpletask2/migrations/0005_alter_simpletaskchannel_options.py
django_simpletask2/migrations/__init__.py
django_simpletask2/static/django_simpletask2/css/django_simpletask2.css
django_simpletask2/static/django_simpletask2/js/django_simpletask2.js
django_simpletask2-0.1.12.dist-info/LICENSE
django_simpletask2-0.1.12.dist-info/METADATA
django_simpletask2-0.1.12.dist-info/WHEEL
django_simpletask2-0.1.12.dist-info/top_level.txt
django_simpletask2-0.1.12.dist-info/RECORD
