Metadata-Version: 2.1
Name: django-simpletask2
Version: 0.1.12
Summary: A simple asynchronous task manager based on the Django framework. All business logic written in a custom task data model. Tasks are triggered by a Redis queue.
Author: Chang TianQun
Maintainer: Chang TianQun
License: MIT
Keywords: django-simpletask2
Classifier: Development Status :: 5 - Production/Stable
Classifier: Intended Audience :: Developers
Classifier: Topic :: Software Development :: Libraries :: Python Modules
Classifier: License :: OSI Approved :: MIT License
Classifier: Programming Language :: Python :: 3
Classifier: Programming Language :: Python :: 3 :: Only
License-File: LICENSE
Requires-Dist: django
Requires-Dist: django-redis
Requires-Dist: django-static-fontawesome
Requires-Dist: django-static-jquery-ui
Requires-Dist: django-middleware-global-request
Requires-Dist: globallock
